micropython_as6212/__init__.py
micropython_as6212/as6212.py
micropython_as6212/i2c_helpers.py
micropython_as6212-0.2.0.dist-info/LICENSE
micropython_as6212-0.2.0.dist-info/METADATA
micropython_as6212-0.2.0.dist-info/WHEEL
micropython_as6212-0.2.0.dist-info/top_level.txt
micropython_as6212-0.2.0.dist-info/RECORD
