Metadata-Version: 2.1
Name: micropython-as6212
Version: 0.2.0
Summary: MicroPython Library for the ASM AS6212 Temperature Sensor
Author-email: JDM <xxyx@mailmeto.mozmail.com>
License: MIT
Project-URL: Homepage, https://github.com/jposada202020/MicroPython_AS6212
Keywords: sensor,micropython,as6212,temperature,micropython,asm,as6212,driver,sensor
Classifier: Intended Audience :: Developers
Classifier: Topic :: Software Development :: Libraries
Classifier: Topic :: Software Development :: Embedded Systems
Classifier: Topic :: System :: Hardware
Classifier: License :: OSI Approved :: MIT License
Classifier: Programming Language :: Python :: Implementation :: MicroPython
License-File: LICENSE
